pyquest/__init__.py
pyquest/constants.py
pyquest/interactive_tutorial.py
pyquest/logger.py
pyquest/mesa_shell.py
pyquest/posix_shell_commands.py
pyquest/self_play_fun.py
pyquest/shell.broke.py
pyquest/shell.py
pyquest/status.py
pyquest/utils.py
pythonny_quest-0.1.2.dist-info/METADATA
pythonny_quest-0.1.2.dist-info/WHEEL
pythonny_quest-0.1.2.dist-info/entry_points.txt
pythonny_quest-0.1.2.dist-info/RECORD
